wagtail_thumbnail_choice_block/__init__.py
wagtail_thumbnail_choice_block/blocks.py
wagtail_thumbnail_choice_block/wagtail_hooks.py
wagtail_thumbnail_choice_block/widgets.py
wagtail_thumbnail_choice_block/static/wagtail_thumbnail_choice_block/css/thumbnail-choice-block.css
wagtail_thumbnail_choice_block/static/wagtail_thumbnail_choice_block/js/thumbnail-choice-block.js
wagtail_thumbnail_choice_block/templates/wagtail_thumbnail_choice_block/widgets/thumbnail_radio_select.html
wagtail_thumbnail_choice_block-0.1.4.dist-info/licenses/LICENSE
wagtail_thumbnail_choice_block-0.1.4.dist-info/METADATA
wagtail_thumbnail_choice_block-0.1.4.dist-info/WHEEL
wagtail_thumbnail_choice_block-0.1.4.dist-info/top_level.txt
wagtail_thumbnail_choice_block-0.1.4.dist-info/RECORD
