Metadata-Version: 2.4
Name: wagtail-thumbnail-choice-block
Version: 0.1.4
Summary: A Wagtail block that displays thumbnail images for choice fields
Author: Lincoln Loop
License: MPL-2.0
Project-URL: Homepage, https://github.com/lincolnloop/wagtail-thumbnail-choice-block
Project-URL: Repository, https://github.com/lincolnloop/wagtail-thumbnail-choice-block
Project-URL: Issues, https://github.com/lincolnloop/wagtail-thumbnail-choice-block/issues
Classifier: Development Status :: 4 - Beta
Classifier: Environment :: Web Environment
Classifier: Framework :: Django
Classifier: Framework :: Django :: 4.2
Classifier: Framework :: Django :: 5.0
Classifier: Framework :: Django :: 5.1
Classifier: Framework :: Django :: 5.2
Classifier: Framework :: Wagtail
Classifier: Framework :: Wagtail :: 5
Classifier: Framework :: Wagtail :: 6
Classifier: Framework :: Wagtail :: 7
Classifier: Intended Audience :: Developers
Classifier: Operating System :: OS Independent
Classifier: Programming Language :: Python
Classifier: Programming Language :: Python :: 3
Classifier: Programming Language :: Python :: 3.10
Classifier: Programming Language :: Python :: 3.11
Classifier: Programming Language :: Python :: 3.12
Classifier: Programming Language :: Python :: 3.13
Classifier: Programming Language :: Python :: 3.14
Classifier: Topic :: Internet :: WWW/HTTP
Classifier: Topic :: Internet :: WWW/HTTP :: Dynamic Content
Requires-Python: >=3.10
License-File: LICENSE
Requires-Dist: Django>=4.2
Requires-Dist: wagtail>=5.0
Provides-Extra: dev
Requires-Dist: pytest>=7.0; extra == "dev"
Requires-Dist: pytest-django>=4.5; extra == "dev"
Requires-Dist: pytest-cov>=4.0; extra == "dev"
Requires-Dist: django-taggit>=3.0; extra == "dev"
Requires-Dist: ruff; extra == "dev"
Provides-Extra: accessibility
Requires-Dist: selenium>=4.0; extra == "accessibility"
Requires-Dist: selenium-axe-python>=2.1; extra == "accessibility"
Provides-Extra: test
Requires-Dist: pytest>=7.0; extra == "test"
Requires-Dist: pytest-django>=4.5; extra == "test"
Requires-Dist: pytest-cov>=4.0; extra == "test"
Requires-Dist: django-taggit>=3.0; extra == "test"
Dynamic: license-file
